kubeflow/__init__.py
kubeflow/tfjob/__init__.py
kubeflow/tfjob/api_client.py
kubeflow/tfjob/configuration.py
kubeflow/tfjob/rest.py
kubeflow/tfjob/api/__init__.py
kubeflow/tfjob/api/tf_job_client.py
kubeflow/tfjob/api/tf_job_watch.py
kubeflow/tfjob/constants/__init__.py
kubeflow/tfjob/constants/constants.py
kubeflow/tfjob/models/__init__.py
kubeflow/tfjob/models/v1_job_condition.py
kubeflow/tfjob/models/v1_job_status.py
kubeflow/tfjob/models/v1_replica_spec.py
kubeflow/tfjob/models/v1_replica_status.py
kubeflow/tfjob/models/v1_tf_job.py
kubeflow/tfjob/models/v1_tf_job_list.py
kubeflow/tfjob/models/v1_tf_job_spec.py
kubeflow/tfjob/models/v1_time.py
kubeflow/tfjob/utils/__init__.py
kubeflow/tfjob/utils/utils.py
test/__init__.py
test/test_e2e.py
test/test_v1_job_condition.py
test/test_v1_job_status.py
test/test_v1_replica_spec.py
test/test_v1_replica_status.py
test/test_v1_tf_job.py
test/test_v1_tf_job_list.py
test/test_v1_tf_job_spec.py
kubeflow_tfjob-0.1.3.dist-info/METADATA
kubeflow_tfjob-0.1.3.dist-info/WHEEL
kubeflow_tfjob-0.1.3.dist-info/top_level.txt
kubeflow_tfjob-0.1.3.dist-info/RECORD
